logous/__init__.py
logous/basemodel.py
logous/churn/__init__.py
logous/churn/logouschurnutils.py
logous/feature_generation/__init__.py
logous/feature_generation/logousrfmutils.py
logous/segmentation/__init__.py
logous/segmentation/logoussegmentationutils.py
logous/time_series/__init__.py
logous/time_series/logousarimautils.py
logous/time_series/logousholtandwinterutils.py
logous/time_series/logouslstmutils.py
logouslibrary-0.0.3.dist-info/LICENSE.txt
logouslibrary-0.0.3.dist-info/METADATA
logouslibrary-0.0.3.dist-info/WHEEL
logouslibrary-0.0.3.dist-info/top_level.txt
logouslibrary-0.0.3.dist-info/RECORD
