Metadata-Version: 2.1
Name: logouslibrary
Version: 0.0.3
Summary: LogoUS machine learning utility package
Home-page: http://en.logo.com.tr/en
Author: Logo
Author-email: Abdussamet.Dumankaya@logo.com.tr
License: LICENSE.txt
Platform: UNKNOWN
Classifier: Programming Language :: Python :: 3
Classifier: License :: OSI Approved :: MIT License
Classifier: Operating System :: OS Independent
Requires-Dist: setuptools (==41.0.1)
Requires-Dist: tensorflow (==1.12.0)
Requires-Dist: xgboost (==0.80)
Requires-Dist: pandas (==0.23.4)
Requires-Dist: pyramid-arima (==0.9.0)
Requires-Dist: scikit-learn (==0.21.2)
Requires-Dist: statsmodels (==0.9.0)
